opcsim/__init__.py
opcsim/distributions.py
opcsim/equations/__init__.py
opcsim/equations/cdf.py
opcsim/equations/pdf.py
opcsim/metrics.py
opcsim/mie.py
opcsim/models.py
opcsim/plots.py
opcsim/rc_style.py
opcsim/utils.py
opcsim-1.0.0.dist-info/LICENSE
opcsim-1.0.0.dist-info/WHEEL
opcsim-1.0.0.dist-info/METADATA
opcsim-1.0.0.dist-info/RECORD
