Metadata-Version: 2.1
Name: opcsim
Version: 1.0.0
Summary: OPCSIM: simulating low-cost optical particle counters
Home-page: https://dhhagan.github.io/opcsim/
License: MIT
Keywords: aerosols,atmospheric chemistry
Author: David H Hagan
Author-email: dhagan@mit.edu
Maintainer: David H Hagan
Maintainer-email: dhagan@mit.edu
Requires-Python: >=3.6.1,<4.0.0
Classifier: License :: OSI Approved :: MIT License
Classifier: Programming Language :: Python :: 3
Classifier: Programming Language :: Python :: 3.7
Classifier: Programming Language :: Python :: 3.8
Classifier: Programming Language :: Python :: 3.9
Requires-Dist: matplotlib (>=3.2.1,<4.0.0)
Requires-Dist: numpy (>=1.18.4,<2.0.0)
Requires-Dist: pandas (>=1.0.3,<2.0.0)
Requires-Dist: scipy (>=1.4.1,<2.0.0)
Requires-Dist: seaborn (>=0.10.1,<0.11.0)
Project-URL: Bug Tracker, https://github.com/dhhagan/opcsim/issues
Project-URL: Documentation, https://dhhagan.github.io/opcsim/
Project-URL: Repository, https://github.com/dhhagan/opcsim
